{
  "zones": [
    {
      "name": "Zone 1",
      "color": "yellow",
      "coords": [
        [26.2140, 81.2530],
        [26.2200, 81.2630],
        [26.2140, 81.2730],
        [26.1940, 81.2730],
        [26.1940, 81.2530]
      ]
    },
    {
      "name": "Chowk Bazaar",
      "color": "yellow",
      "coords": [
        [23.261577, 77.401257],
        [23.259170, 77.399096],
        [23.256651, 77.401897],
        [23.259390, 77.405218]
      ]
    },
    {
      "name": "Kerwa Dam",
      "color": "yellow",
      "coords": [
        [23.164043, 77.388763],
        [23.181178, 77.359806],
        [23.168888, 77.343836],
        [23.143109, 77.357855]
      ]
    },
    {
      "name": "Kaliyasot Dam",
      "color": "yellow",
      "coords": [
        [23.209126, 77.376924],
        [23.204244, 77.409194],
        [23.192038, 77.407335],
        [23.187583, 77.381904],
        [23.206685, 77.367230]
      ]
    },
    {
      "name": "Lalghati",
      "color": "yellow",
      "coords": [
        [23.292712, 77.350332],
        [23.293943, 77.364631],
        [23.283447, 77.372547],
        [23.289017, 77.380718],
        [23.284678, 77.382889],
        [23.271894, 77.376569],
        [23.264916, 77.359397],
        [23.280339, 77.350970],
        [23.293474, 77.353651]
      ]
    },
    {
      "name": "New Market",
      "color": "yellow",
      "coords": [
        [23.235749, 77.398885],
        [23.233934, 77.399776],
        [23.233934, 77.399776],
        [23.237425, 77.401289]
      ]
    },
    {
      "name": "Upper Lake",
      "color": "yellow",
      "coords": [
        [23.237634, 77.257367],
        [23.271543, 77.325860],
        [23.253880, 77.400704],
        [23.207977, 77.378731],
        [23.227381, 77.317620],
        [23.243470, 77.319852]
      ]
    },
    {
      "name": "Old Union Carbide Factory",
      "color": "red",
      "coords": [
        [23.283173, 77.408502],
        [23.282361, 77.409981],
        [23.282299, 77.408584]
      ]
    },
    {
      "name": "Aypdhya Bypass Road",
      "color": "red",
      "coords": [23.275590, 77.463559],
      "radius": 1000
    },
    {
      "name": "Zone 2",
      "color": "red",
      "coords": [26.2140, 81.2530],
      "radius": 1000
    }
  ],
  "places": [
    {
      "name": "Indra Garden",
      "type": "Park",
      "coords": [26.204694, 81.251379]
    },
    {
      "name": "Saheed Smarak",
      "type": "Tourist Spot",
      "coords": [26.202021, 81.247152]
    },
    {
      "name": "Janeshwar Mishra Park",
      "type": "Park",
      "coords": [26.8700, 80.9800]
    },
    {
      "name": "Hotel Taj",
      "type": "Hotel",
      "coords": [26.8500, 80.9490]
    },
    {
      "name": "La Place",
      "type": "Restaurant",
      "coords": [26.8550, 80.9480]
    }
  ]
}
